polyadicqml/__init__.py
polyadicqml/circuitBuilder.py
polyadicqml/circuitML.py
polyadicqml/quantumClassifier.py
polyadicqml/utility.py
polyadicqml/manyq/__init__.py
polyadicqml/manyq/mqBuilder.py
polyadicqml/manyq/mqCircuitML.py
polyadicqml/qiskit/__init__.py
polyadicqml/qiskit/qkBuilder.py
polyadicqml/qiskit/qkCircuitML.py
polyadicqml/qiskit/qkParallelML.py
polyadicqml/qiskit/utility/__init__.py
polyadicqml/qiskit/utility/backends.py
polyadicqml-0.1.0b4.dist-info/LICENSE
polyadicqml-0.1.0b4.dist-info/METADATA
polyadicqml-0.1.0b4.dist-info/WHEEL
polyadicqml-0.1.0b4.dist-info/top_level.txt
polyadicqml-0.1.0b4.dist-info/RECORD
