Metadata-Version: 2.1
Name: polyadicqml
Version: 0.1.0b4
Summary: High level API to define, train and deploy Polyadic Quantum Machine Learning models
Home-page: https://github.com/entropicalabs/polyadicQML
Author: William Cappelletti
Author-email: cappelletti.william@gmail.com
License: Apache 2.0
Platform: UNKNOWN
Classifier: Programming Language :: Python :: 3
Classifier: Operating System :: OS Independent
Classifier: Development Status :: 4 - Beta
Classifier: License :: OSI Approved :: Apache Software License
Classifier: Intended Audience :: Science/Research
Classifier: Topic :: Scientific/Engineering :: Artificial Intelligence
Requires-Python: >=3.6
Requires-Dist: numpy
Requires-Dist: scipy
Requires-Dist: sklearn
Requires-Dist: qiskit
Requires-Dist: manyq
Requires-Dist: tqdm
